README.md
setup.cfg
setup.py
small_timer/__init__.py
small_timer.egg-info/PKG-INFO
small_timer.egg-info/SOURCES.txt
small_timer.egg-info/dependency_links.txt
small_timer.egg-info/top_level.txt