Metadata-Version: 2.1
Name: small-timer
Version: 1.0.9
Summary: A miniature timer that does the same thing as a regular timer
Author: Dolenko10.0Artem10.0
Author-email: artemdolenko.ua@gmail.com
Classifier: Programming Language :: Python :: 3
Classifier: License :: OSI Approved :: MIT License
Classifier: Operating System :: OS Independent
Requires-Python: >=3.6
